shadai/__init__.py
shadai/__version__.py
shadai/analyzers.py
shadai/async_job.py
shadai/client.py
shadai/error_handler.py
shadai/exceptions.py
shadai/models.py
shadai/session.py
shadai/timing.py
shadai/tools.py
shadai/types.py
shadai-0.1.33.dist-info/licenses/LICENSE
shadai-0.1.33.dist-info/METADATA
shadai-0.1.33.dist-info/WHEEL
shadai-0.1.33.dist-info/top_level.txt
shadai-0.1.33.dist-info/RECORD
