Metadata-Version: 2.4
Name: shadai
Version: 0.1.33
Summary: SHADAI Client
Author: SHADAI GROUP
Author-email: SHADAI GROUP <jaisir@shadai.ai>
Keywords: shadai,ai,rag,machine-learning,nlp,knowledge-base,mcp,async
Requires-Python: >=3.10
License-File: LICENSE
Requires-Dist: aiohttp>=3.8.0
Requires-Dist: pydantic>=2.0.0
Requires-Dist: langchain-core==1.0.0a8
Requires-Dist: python-dotenv==1.1.1
Requires-Dist: streamlit>=1.28.0
Provides-Extra: dev
Requires-Dist: pytest>=7.0; extra == "dev"
Requires-Dist: pytest-asyncio>=0.21.0; extra == "dev"
Requires-Dist: black>=23.0; extra == "dev"
Requires-Dist: mypy>=1.0; extra == "dev"
Requires-Dist: ruff>=0.1.0; extra == "dev"
Dynamic: author
Dynamic: license-file
